dss/IActiveClass.py
dss/IBus.py
dss/ICNData.py
dss/ICapControls.py
dss/ICapacitors.py
dss/ICircuit.py
dss/ICktElement.py
dss/ICtrlQueue.py
dss/IDSS.py
dss/IDSSElement.py
dss/IDSSEvents.py
dss/IDSSProgress.py
dss/IDSSProperty.py
dss/IDSS_Executive.py
dss/IDSSimComs.py
dss/IError.py
dss/IFuses.py
dss/IGICSources.py
dss/IGenerators.py
dss/IISources.py
dss/ILineCodes.py
dss/ILineGeometries.py
dss/ILineSpacings.py
dss/ILines.py
dss/ILoadShapes.py
dss/ILoads.py
dss/IMeters.py
dss/IMonitors.py
dss/IPDElements.py
dss/IPVSystems.py
dss/IParallel.py
dss/IParser.py
dss/IReactors.py
dss/IReclosers.py
dss/IReduceCkt.py
dss/IRegControls.py
dss/IRelays.py
dss/ISensors.py
dss/ISettings.py
dss/ISolution.py
dss/IStorages.py
dss/ISwtControls.py
dss/ITSData.py
dss/IText.py
dss/ITopology.py
dss/ITransformers.py
dss/IVsources.py
dss/IWireData.py
dss/IXYCurves.py
dss/IYMatrix.py
dss/IZIP.py
dss/__init__.py
dss/_cffi_api_util.py
dss/_types.py
dss/_version.py
dss/enums.py
dss/examples.py
dss/patch_dss_com.py
dss/plot.py
dss/UserModels/__init__.py
dss/UserModels/bases.py
dss/UserModels/wrappers.py
dss/messages/properties-en-US.mo
dss_python-0.15.6.dist-info/METADATA
dss_python-0.15.6.dist-info/WHEEL
dss_python-0.15.6.dist-info/licenses/LICENSE
dss_python-0.15.6.dist-info/RECORD
