Metadata-Version: 2.3
Name: dss-python
Version: 0.15.6
Summary: Python interface (bindings and tools) for OpenDSS. Based on the AltDSS/DSS C-API project, the alternative OpenDSS implementation from DSS-Extensions.org. Multiplatform, API-compatible/drop-in replacement for the COM version of OpenDSS.
Project-URL: Homepage, https://github.com/dss-extensions/DSS-Python
Project-URL: Documentation, https://dss-extensions.org/DSS-Python
Project-URL: Repository, https://github.com/dss-extensions/DSS-Python.git
Project-URL: Bug Tracker, https://github.com/dss-extensions/DSS-Python/issues
Project-URL: Changelog, https://github.com/dss-extensions/DSS-Python/blob/main/docs/changelog.md
Author-email: Paulo Meira <pmeira@ieee.org>, Dheepak Krishnamurthy <me@kdheepak.com>
Maintainer-email: Paulo Meira <pmeira@ieee.org>
License: BSD 3-Clause License
License-File: LICENSE
Keywords: altdss,electric power systems,opendss,opendssdirect,powerflow,short-circuit
Classifier: Development Status :: 5 - Production/Stable
Classifier: Intended Audience :: Education
Classifier: Intended Audience :: Science/Research
Classifier: License :: OSI Approved :: BSD License
Classifier: Programming Language :: Python :: 3.7
Classifier: Programming Language :: Python :: 3.8
Classifier: Programming Language :: Python :: 3.9
Classifier: Programming Language :: Python :: 3.10
Classifier: Programming Language :: Python :: 3.11
Classifier: Programming Language :: Python :: 3.12
Classifier: Programming Language :: Python :: Implementation :: CPython
Classifier: Programming Language :: Python :: Implementation :: PyPy
Classifier: Topic :: Scientific/Engineering
Requires-Python: >=3.7
Requires-Dist: dss-python-backend==0.14.4
Requires-Dist: numpy>=1.21.0
Requires-Dist: typing-extensions<5,>=4.5
Provides-Extra: all
Requires-Dist: altdss; extra == 'all'
Requires-Dist: matplotlib; extra == 'all'
Requires-Dist: opendssdirect-py[extras]; extra == 'all'
Requires-Dist: pandas; extra == 'all'
Requires-Dist: scipy; extra == 'all'
Provides-Extra: plot
Requires-Dist: matplotlib; extra == 'plot'
Requires-Dist: scipy; extra == 'plot'
Provides-Extra: test
Requires-Dist: pandas; extra == 'test'
Requires-Dist: pytest; extra == 'test'
Requires-Dist: ruff; extra == 'test'
Requires-Dist: scipy; extra == 'test'
Requires-Dist: xmldiff; extra == 'test'
